midi_abstraction/__init__.py
midi_abstraction/midi_abstraction.py
midi_abstraction-2.0.2.dist-info/LICENSE
midi_abstraction-2.0.2.dist-info/METADATA
midi_abstraction-2.0.2.dist-info/WHEEL
midi_abstraction-2.0.2.dist-info/top_level.txt
midi_abstraction-2.0.2.dist-info/RECORD
