Metadata-Version: 2.1
Name: midi-abstraction
Version: 2.0.2
Summary: Abstract MIDI pitches into keys, chords, modes, scales, and notes.
Home-page: https://github.com/cyberrumor/midi-abstraction
Author: Marco Silva
Author-email: cyberrumor@gmail.com
Classifier: Programming Language :: Python :: 3.10
Classifier: License :: OSI Approved :: GNU General Public License v3 (GPLv3)
Classifier: Operating System :: OS Independent
Requires-Python: >=3.10
License-File: LICENSE
